{
  "annotations": {
    "list": [
      {
        "builtIn": 1,
        "datasource": { "type": "grafana", "uid": "-- Grafana --" },
        "enable": true,
        "hide": true,
        "iconColor": "rgba(0, 211, 255, 1)",
        "name": "Annotations & Alerts",
        "type": "dashboard"
      }
    ]
  },
  "editable": true,
  "fiscalYearStartMonth": 0,
  "graphTooltip": 1,
  "id": null,
  "links": [],
  "liveNow": false,
  "panels": [
    {
      "collapsed": false,
      "gridPos": { "h": 1, "w": 24, "x": 0, "y": 0 },
      "id": 100,
      "panels": [],
      "title": "🎯 Namespace Overview: $namespace",
      "type": "row"
    },
    {
      "datasource": { "type": "prometheus", "uid": "prometheus" },
      "fieldConfig": {
        "defaults": {
          "color": { "mode": "thresholds" },
          "mappings": [],
          "thresholds": { "mode": "absolute", "steps": [{ "color": "green", "value": null }] },
          "unit": "short"
        },
        "overrides": []
      },
      "gridPos": { "h": 4, "w": 4, "x": 0, "y": 1 },
      "id": 1,
      "options": { "colorMode": "value", "graphMode": "none", "justifyMode": "center", "orientation": "auto", "reduceOptions": { "calcs": ["lastNotNull"], "fields": "", "values": false }, "textMode": "auto" },
      "title": "Total Pods",
      "type": "stat",
      "targets": [{ "expr": "count(kube_pod_info{namespace=\"$namespace\"})", "refId": "A" }]
    },
    {
      "datasource": { "type": "prometheus", "uid": "prometheus" },
      "fieldConfig": {
        "defaults": {
          "color": { "mode": "thresholds" },
          "mappings": [],
          "thresholds": { "mode": "absolute", "steps": [{ "color": "green", "value": null }] },
          "unit": "short"
        },
        "overrides": []
      },
      "gridPos": { "h": 4, "w": 4, "x": 4, "y": 1 },
      "id": 2,
      "options": { "colorMode": "value", "graphMode": "none", "justifyMode": "center", "orientation": "auto", "reduceOptions": { "calcs": ["lastNotNull"], "fields": "", "values": false }, "textMode": "auto" },
      "title": "Running",
      "type": "stat",
      "targets": [{ "expr": "count(kube_pod_status_phase{namespace=\"$namespace\", phase=\"Running\"})", "refId": "A" }]
    },
    {
      "datasource": { "type": "prometheus", "uid": "prometheus" },
      "fieldConfig": {
        "defaults": {
          "color": { "mode": "thresholds" },
          "mappings": [],
          "thresholds": { "mode": "absolute", "steps": [{ "color": "green", "value": null }, { "color": "yellow", "value": 1 }, { "color": "red", "value": 3 }] },
          "unit": "short"
        },
        "overrides": []
      },
      "gridPos": { "h": 4, "w": 4, "x": 8, "y": 1 },
      "id": 3,
      "options": { "colorMode": "background", "graphMode": "none", "justifyMode": "center", "orientation": "auto", "reduceOptions": { "calcs": ["lastNotNull"], "fields": "", "values": false }, "textMode": "auto" },
      "title": "Pending",
      "type": "stat",
      "targets": [{ "expr": "count(kube_pod_status_phase{namespace=\"$namespace\", phase=\"Pending\"}) or vector(0)", "refId": "A" }]
    },
    {
      "datasource": { "type": "prometheus", "uid": "prometheus" },
      "fieldConfig": {
        "defaults": {
          "color": { "mode": "thresholds" },
          "mappings": [],
          "thresholds": { "mode": "absolute", "steps": [{ "color": "green", "value": null }, { "color": "red", "value": 1 }] },
          "unit": "short"
        },
        "overrides": []
      },
      "gridPos": { "h": 4, "w": 4, "x": 12, "y": 1 },
      "id": 4,
      "options": { "colorMode": "background", "graphMode": "none", "justifyMode": "center", "orientation": "auto", "reduceOptions": { "calcs": ["lastNotNull"], "fields": "", "values": false }, "textMode": "auto" },
      "title": "Failed",
      "type": "stat",
      "targets": [{ "expr": "count(kube_pod_status_phase{namespace=\"$namespace\", phase=\"Failed\"}) or vector(0)", "refId": "A" }]
    },
    {
      "datasource": { "type": "prometheus", "uid": "prometheus" },
      "fieldConfig": {
        "defaults": {
          "color": { "mode": "thresholds" },
          "mappings": [],
          "thresholds": { "mode": "absolute", "steps": [{ "color": "green", "value": null }, { "color": "orange", "value": 1 }, { "color": "red", "value": 5 }] },
          "unit": "short"
        },
        "overrides": []
      },
      "gridPos": { "h": 4, "w": 4, "x": 16, "y": 1 },
      "id": 5,
      "options": { "colorMode": "background", "graphMode": "none", "justifyMode": "center", "orientation": "auto", "reduceOptions": { "calcs": ["lastNotNull"], "fields": "", "values": false }, "textMode": "auto" },
      "title": "Restarts (1h)",
      "type": "stat",
      "targets": [{ "expr": "sum(increase(kube_pod_container_status_restarts_total{namespace=\"$namespace\"}[1h])) or vector(0)", "refId": "A" }]
    },
    {
      "datasource": { "type": "prometheus", "uid": "prometheus" },
      "fieldConfig": {
        "defaults": {
          "color": { "mode": "thresholds" },
          "mappings": [],
          "thresholds": { "mode": "absolute", "steps": [{ "color": "green", "value": null }] },
          "unit": "short"
        },
        "overrides": []
      },
      "gridPos": { "h": 4, "w": 4, "x": 20, "y": 1 },
      "id": 6,
      "options": { "colorMode": "value", "graphMode": "none", "justifyMode": "center", "orientation": "auto", "reduceOptions": { "calcs": ["lastNotNull"], "fields": "", "values": false }, "textMode": "auto" },
      "title": "Deployments",
      "type": "stat",
      "targets": [{ "expr": "count(kube_deployment_labels{namespace=\"$namespace\"}) or vector(0)", "refId": "A" }]
    },
    {
      "collapsed": false,
      "gridPos": { "h": 1, "w": 24, "x": 0, "y": 5 },
      "id": 101,
      "panels": [],
      "title": "📊 Resource Usage",
      "type": "row"
    },
    {
      "datasource": { "type": "prometheus", "uid": "prometheus" },
      "fieldConfig": {
        "defaults": {
          "color": { "mode": "palette-classic" },
          "custom": { "axisCenteredZero": false, "axisColorMode": "text", "axisLabel": "CPU Cores", "axisPlacement": "auto", "barAlignment": 0, "drawStyle": "line", "fillOpacity": 20, "gradientMode": "opacity", "hideFrom": { "legend": false, "tooltip": false, "viz": false }, "lineInterpolation": "smooth", "lineWidth": 2, "pointSize": 5, "scaleDistribution": { "type": "linear" }, "showPoints": "never", "spanNulls": false, "stacking": { "group": "A", "mode": "normal" }, "thresholdsStyle": { "mode": "off" } },
          "mappings": [],
          "thresholds": { "mode": "absolute", "steps": [{ "color": "green", "value": null }] },
          "unit": "short"
        },
        "overrides": []
      },
      "gridPos": { "h": 8, "w": 12, "x": 0, "y": 6 },
      "id": 10,
      "options": { "legend": { "calcs": ["mean", "max"], "displayMode": "table", "placement": "bottom", "showLegend": true }, "tooltip": { "mode": "multi", "sort": "desc" } },
      "title": "CPU Usage by Pod",
      "type": "timeseries",
      "targets": [{ "expr": "sum by (pod) (rate(container_cpu_usage_seconds_total{namespace=\"$namespace\", container!=\"\", container!=\"POD\"}[5m]))", "legendFormat": "{{pod}}", "refId": "A" }]
    },
    {
      "datasource": { "type": "prometheus", "uid": "prometheus" },
      "fieldConfig": {
        "defaults": {
          "color": { "mode": "palette-classic" },
          "custom": { "axisCenteredZero": false, "axisColorMode": "text", "axisLabel": "", "axisPlacement": "auto", "barAlignment": 0, "drawStyle": "line", "fillOpacity": 20, "gradientMode": "opacity", "hideFrom": { "legend": false, "tooltip": false, "viz": false }, "lineInterpolation": "smooth", "lineWidth": 2, "pointSize": 5, "scaleDistribution": { "type": "linear" }, "showPoints": "never", "spanNulls": false, "stacking": { "group": "A", "mode": "normal" }, "thresholdsStyle": { "mode": "off" } },
          "mappings": [],
          "thresholds": { "mode": "absolute", "steps": [{ "color": "green", "value": null }] },
          "unit": "bytes"
        },
        "overrides": []
      },
      "gridPos": { "h": 8, "w": 12, "x": 12, "y": 6 },
      "id": 11,
      "options": { "legend": { "calcs": ["mean", "max"], "displayMode": "table", "placement": "bottom", "showLegend": true }, "tooltip": { "mode": "multi", "sort": "desc" } },
      "title": "Memory Usage by Pod",
      "type": "timeseries",
      "targets": [{ "expr": "sum by (pod) (container_memory_working_set_bytes{namespace=\"$namespace\", container!=\"\", container!=\"POD\"})", "legendFormat": "{{pod}}", "refId": "A" }]
    },
    {
      "datasource": { "type": "prometheus", "uid": "prometheus" },
      "fieldConfig": {
        "defaults": {
          "color": { "mode": "thresholds" },
          "mappings": [],
          "thresholds": { "mode": "absolute", "steps": [{ "color": "green", "value": null }] },
          "unit": "short"
        },
        "overrides": []
      },
      "gridPos": { "h": 4, "w": 6, "x": 0, "y": 14 },
      "id": 12,
      "options": { "colorMode": "value", "graphMode": "area", "justifyMode": "center", "orientation": "auto", "reduceOptions": { "calcs": ["lastNotNull"], "fields": "", "values": false }, "textMode": "auto" },
      "title": "Total CPU Usage",
      "type": "stat",
      "targets": [{ "expr": "sum(rate(container_cpu_usage_seconds_total{namespace=\"$namespace\", container!=\"\", container!=\"POD\"}[5m]))", "refId": "A" }]
    },
    {
      "datasource": { "type": "prometheus", "uid": "prometheus" },
      "fieldConfig": {
        "defaults": {
          "color": { "mode": "thresholds" },
          "mappings": [],
          "thresholds": { "mode": "absolute", "steps": [{ "color": "green", "value": null }] },
          "unit": "bytes"
        },
        "overrides": []
      },
      "gridPos": { "h": 4, "w": 6, "x": 6, "y": 14 },
      "id": 13,
      "options": { "colorMode": "value", "graphMode": "area", "justifyMode": "center", "orientation": "auto", "reduceOptions": { "calcs": ["lastNotNull"], "fields": "", "values": false }, "textMode": "auto" },
      "title": "Total Memory Usage",
      "type": "stat",
      "targets": [{ "expr": "sum(container_memory_working_set_bytes{namespace=\"$namespace\", container!=\"\", container!=\"POD\"})", "refId": "A" }]
    },
    {
      "datasource": { "type": "prometheus", "uid": "prometheus" },
      "fieldConfig": {
        "defaults": {
          "color": { "mode": "thresholds" },
          "mappings": [],
          "thresholds": { "mode": "absolute", "steps": [{ "color": "green", "value": null }] },
          "unit": "Bps"
        },
        "overrides": []
      },
      "gridPos": { "h": 4, "w": 6, "x": 12, "y": 14 },
      "id": 14,
      "options": { "colorMode": "value", "graphMode": "area", "justifyMode": "center", "orientation": "auto", "reduceOptions": { "calcs": ["lastNotNull"], "fields": "", "values": false }, "textMode": "auto" },
      "title": "Network In",
      "type": "stat",
      "targets": [{ "expr": "sum(rate(container_network_receive_bytes_total{namespace=\"$namespace\"}[5m]))", "refId": "A" }]
    },
    {
      "datasource": { "type": "prometheus", "uid": "prometheus" },
      "fieldConfig": {
        "defaults": {
          "color": { "mode": "thresholds" },
          "mappings": [],
          "thresholds": { "mode": "absolute", "steps": [{ "color": "green", "value": null }] },
          "unit": "Bps"
        },
        "overrides": []
      },
      "gridPos": { "h": 4, "w": 6, "x": 18, "y": 14 },
      "id": 15,
      "options": { "colorMode": "value", "graphMode": "area", "justifyMode": "center", "orientation": "auto", "reduceOptions": { "calcs": ["lastNotNull"], "fields": "", "values": false }, "textMode": "auto" },
      "title": "Network Out",
      "type": "stat",
      "targets": [{ "expr": "sum(rate(container_network_transmit_bytes_total{namespace=\"$namespace\"}[5m]))", "refId": "A" }]
    },
    {
      "collapsed": false,
      "gridPos": { "h": 1, "w": 24, "x": 0, "y": 18 },
      "id": 102,
      "panels": [],
      "title": "🌐 Network I/O",
      "type": "row"
    },
    {
      "datasource": { "type": "prometheus", "uid": "prometheus" },
      "fieldConfig": {
        "defaults": {
          "color": { "mode": "palette-classic" },
          "custom": { "axisCenteredZero": false, "axisColorMode": "text", "axisLabel": "", "axisPlacement": "auto", "barAlignment": 0, "drawStyle": "line", "fillOpacity": 20, "gradientMode": "opacity", "hideFrom": { "legend": false, "tooltip": false, "viz": false }, "lineInterpolation": "smooth", "lineWidth": 2, "pointSize": 5, "scaleDistribution": { "type": "linear" }, "showPoints": "never", "spanNulls": false, "stacking": { "group": "A", "mode": "none" }, "thresholdsStyle": { "mode": "off" } },
          "mappings": [],
          "thresholds": { "mode": "absolute", "steps": [{ "color": "green", "value": null }] },
          "unit": "Bps"
        },
        "overrides": []
      },
      "gridPos": { "h": 8, "w": 12, "x": 0, "y": 19 },
      "id": 20,
      "options": { "legend": { "calcs": ["mean", "max"], "displayMode": "table", "placement": "bottom", "showLegend": true }, "tooltip": { "mode": "multi", "sort": "desc" } },
      "title": "Network Receive by Pod",
      "type": "timeseries",
      "targets": [{ "expr": "sum by (pod) (rate(container_network_receive_bytes_total{namespace=\"$namespace\", pod!=\"\"}[5m]))", "legendFormat": "{{pod}}", "refId": "A" }]
    },
    {
      "datasource": { "type": "prometheus", "uid": "prometheus" },
      "fieldConfig": {
        "defaults": {
          "color": { "mode": "palette-classic" },
          "custom": { "axisCenteredZero": false, "axisColorMode": "text", "axisLabel": "", "axisPlacement": "auto", "barAlignment": 0, "drawStyle": "line", "fillOpacity": 20, "gradientMode": "opacity", "hideFrom": { "legend": false, "tooltip": false, "viz": false }, "lineInterpolation": "smooth", "lineWidth": 2, "pointSize": 5, "scaleDistribution": { "type": "linear" }, "showPoints": "never", "spanNulls": false, "stacking": { "group": "A", "mode": "none" }, "thresholdsStyle": { "mode": "off" } },
          "mappings": [],
          "thresholds": { "mode": "absolute", "steps": [{ "color": "green", "value": null }] },
          "unit": "Bps"
        },
        "overrides": []
      },
      "gridPos": { "h": 8, "w": 12, "x": 12, "y": 19 },
      "id": 21,
      "options": { "legend": { "calcs": ["mean", "max"], "displayMode": "table", "placement": "bottom", "showLegend": true }, "tooltip": { "mode": "multi", "sort": "desc" } },
      "title": "Network Transmit by Pod",
      "type": "timeseries",
      "targets": [{ "expr": "sum by (pod) (rate(container_network_transmit_bytes_total{namespace=\"$namespace\", pod!=\"\"}[5m]))", "legendFormat": "{{pod}}", "refId": "A" }]
    },
    {
      "collapsed": false,
      "gridPos": { "h": 1, "w": 24, "x": 0, "y": 27 },
      "id": 103,
      "panels": [],
      "title": "💾 Storage",
      "type": "row"
    },
    {
      "datasource": { "type": "prometheus", "uid": "prometheus" },
      "fieldConfig": {
        "defaults": {
          "color": { "mode": "thresholds" },
          "mappings": [],
          "max": 1,
          "min": 0,
          "thresholds": { "mode": "percentage", "steps": [{ "color": "green", "value": null }, { "color": "yellow", "value": 70 }, { "color": "orange", "value": 80 }, { "color": "red", "value": 90 }] },
          "unit": "percentunit"
        },
        "overrides": []
      },
      "gridPos": { "h": 8, "w": 12, "x": 0, "y": 28 },
      "id": 30,
      "options": { "displayMode": "lcd", "minVizHeight": 10, "minVizWidth": 0, "orientation": "horizontal", "reduceOptions": { "calcs": ["lastNotNull"], "fields": "", "values": false }, "showUnfilled": true, "valueMode": "color" },
      "title": "PVC Usage %",
      "type": "bargauge",
      "targets": [{ "expr": "(kubelet_volume_stats_used_bytes{namespace=\"$namespace\"} / kubelet_volume_stats_capacity_bytes{namespace=\"$namespace\"})", "legendFormat": "{{persistentvolumeclaim}}", "refId": "A" }]
    },
    {
      "datasource": { "type": "prometheus", "uid": "prometheus" },
      "fieldConfig": {
        "defaults": {
          "color": { "mode": "palette-classic" },
          "custom": { "axisCenteredZero": false, "axisColorMode": "text", "axisLabel": "", "axisPlacement": "auto", "barAlignment": 0, "drawStyle": "line", "fillOpacity": 20, "gradientMode": "opacity", "hideFrom": { "legend": false, "tooltip": false, "viz": false }, "lineInterpolation": "smooth", "lineWidth": 2, "pointSize": 5, "scaleDistribution": { "type": "linear" }, "showPoints": "never", "spanNulls": false, "stacking": { "group": "A", "mode": "none" }, "thresholdsStyle": { "mode": "off" } },
          "mappings": [],
          "thresholds": { "mode": "absolute", "steps": [{ "color": "green", "value": null }] },
          "unit": "bytes"
        },
        "overrides": []
      },
      "gridPos": { "h": 8, "w": 12, "x": 12, "y": 28 },
      "id": 31,
      "options": { "legend": { "calcs": ["mean", "max"], "displayMode": "table", "placement": "bottom", "showLegend": true }, "tooltip": { "mode": "multi", "sort": "desc" } },
      "title": "PVC Used Space Over Time",
      "type": "timeseries",
      "targets": [{ "expr": "kubelet_volume_stats_used_bytes{namespace=\"$namespace\"}", "legendFormat": "{{persistentvolumeclaim}}", "refId": "A" }]
    },
    {
      "collapsed": false,
      "gridPos": { "h": 1, "w": 24, "x": 0, "y": 36 },
      "id": 104,
      "panels": [],
      "title": "🚀 Workloads",
      "type": "row"
    },
    {
      "datasource": { "type": "prometheus", "uid": "prometheus" },
      "fieldConfig": {
        "defaults": {
          "color": { "mode": "thresholds" },
          "custom": { "align": "auto", "cellOptions": { "type": "auto" }, "inspect": false },
          "mappings": [],
          "thresholds": { "mode": "absolute", "steps": [{ "color": "green", "value": null }, { "color": "red", "value": 80 }] }
        },
        "overrides": [
          { "matcher": { "id": "byName", "options": "Deployment" }, "properties": [{ "id": "custom.width", "value": 250 }] },
          { "matcher": { "id": "byName", "options": "Available" }, "properties": [{ "id": "custom.cellOptions", "value": { "type": "color-text" } }] },
          { "matcher": { "id": "byName", "options": "Desired" }, "properties": [{ "id": "custom.cellOptions", "value": { "type": "color-text" } }] }
        ]
      },
      "gridPos": { "h": 8, "w": 12, "x": 0, "y": 37 },
      "id": 40,
      "options": { "cellHeight": "sm", "footer": { "countRows": false, "fields": "", "reducer": ["sum"], "show": false }, "showHeader": true },
      "title": "Deployment Status",
      "type": "table",
      "targets": [
        { "expr": "kube_deployment_status_replicas_available{namespace=\"$namespace\"}", "format": "table", "instant": true, "legendFormat": "", "refId": "A" },
        { "expr": "kube_deployment_spec_replicas{namespace=\"$namespace\"}", "format": "table", "instant": true, "legendFormat": "", "refId": "B" }
      ],
      "transformations": [
        { "id": "seriesToColumns", "options": { "byField": "deployment" } },
        { "id": "organize", "options": { "excludeByName": { "Time": true, "Time 1": true, "Time 2": true, "__name__": true, "__name__ 1": true, "__name__ 2": true, "instance": true, "instance 1": true, "instance 2": true, "job": true, "job 1": true, "job 2": true, "namespace": true, "namespace 1": true, "namespace 2": true }, "indexByName": {}, "renameByName": { "Value #A": "Available", "Value #B": "Desired", "deployment": "Deployment" } } }
      ]
    },
    {
      "datasource": { "type": "prometheus", "uid": "prometheus" },
      "fieldConfig": {
        "defaults": {
          "color": { "mode": "palette-classic" },
          "custom": { "axisCenteredZero": false, "axisColorMode": "text", "axisLabel": "", "axisPlacement": "auto", "barAlignment": 0, "drawStyle": "line", "fillOpacity": 0, "gradientMode": "none", "hideFrom": { "legend": false, "tooltip": false, "viz": false }, "lineInterpolation": "stepAfter", "lineWidth": 2, "pointSize": 5, "scaleDistribution": { "type": "linear" }, "showPoints": "never", "spanNulls": false, "stacking": { "group": "A", "mode": "none" }, "thresholdsStyle": { "mode": "off" } },
          "mappings": [],
          "thresholds": { "mode": "absolute", "steps": [{ "color": "green", "value": null }] },
          "unit": "short"
        },
        "overrides": []
      },
      "gridPos": { "h": 8, "w": 12, "x": 12, "y": 37 },
      "id": 41,
      "options": { "legend": { "calcs": [], "displayMode": "list", "placement": "bottom", "showLegend": true }, "tooltip": { "mode": "multi", "sort": "desc" } },
      "title": "Pod Restarts",
      "type": "timeseries",
      "targets": [{ "expr": "increase(kube_pod_container_status_restarts_total{namespace=\"$namespace\"}[5m])", "legendFormat": "{{pod}}", "refId": "A" }]
    },
    {
      "collapsed": false,
      "gridPos": { "h": 1, "w": 24, "x": 0, "y": 45 },
      "id": 105,
      "panels": [],
      "title": "🐳 Container Details",
      "type": "row"
    },
    {
      "datasource": { "type": "prometheus", "uid": "prometheus" },
      "fieldConfig": {
        "defaults": {
          "color": { "mode": "thresholds" },
          "custom": { "align": "auto", "cellOptions": { "type": "auto" }, "inspect": false },
          "mappings": [
            { "options": { "0": { "color": "red", "index": 0, "text": "Not Ready" } }, "type": "value" },
            { "options": { "1": { "color": "green", "index": 1, "text": "Ready" } }, "type": "value" }
          ],
          "thresholds": { "mode": "absolute", "steps": [{ "color": "red", "value": null }, { "color": "green", "value": 1 }] }
        },
        "overrides": [
          { "matcher": { "id": "byName", "options": "Pod" }, "properties": [{ "id": "custom.width", "value": 300 }] },
          { "matcher": { "id": "byName", "options": "Container" }, "properties": [{ "id": "custom.width", "value": 150 }] },
          { "matcher": { "id": "byName", "options": "Ready" }, "properties": [{ "id": "custom.cellOptions", "value": { "type": "color-background" } }] }
        ]
      },
      "gridPos": { "h": 10, "w": 12, "x": 0, "y": 46 },
      "id": 50,
      "options": { "cellHeight": "sm", "footer": { "countRows": false, "fields": "", "reducer": ["sum"], "show": false }, "showHeader": true, "sortBy": [{ "desc": false, "displayName": "Ready" }] },
      "title": "Container Status",
      "type": "table",
      "targets": [
        { "expr": "kube_pod_container_status_ready{namespace=\"$namespace\"}", "format": "table", "instant": true, "legendFormat": "", "refId": "A" }
      ],
      "transformations": [
        { "id": "organize", "options": { "excludeByName": { "Time": true, "__name__": true, "instance": true, "job": true, "namespace": true, "uid": true }, "indexByName": {}, "renameByName": { "Value": "Ready", "container": "Container", "pod": "Pod" } } }
      ]
    },
    {
      "datasource": { "type": "prometheus", "uid": "prometheus" },
      "fieldConfig": {
        "defaults": {
          "color": { "mode": "palette-classic" },
          "custom": { "axisCenteredZero": false, "axisColorMode": "text", "axisLabel": "", "axisPlacement": "auto", "barAlignment": 0, "drawStyle": "line", "fillOpacity": 20, "gradientMode": "opacity", "hideFrom": { "legend": false, "tooltip": false, "viz": false }, "lineInterpolation": "smooth", "lineWidth": 2, "pointSize": 5, "scaleDistribution": { "type": "linear" }, "showPoints": "never", "spanNulls": false, "stacking": { "group": "A", "mode": "none" }, "thresholdsStyle": { "mode": "off" } },
          "mappings": [],
          "thresholds": { "mode": "absolute", "steps": [{ "color": "green", "value": null }] },
          "unit": "bytes"
        },
        "overrides": []
      },
      "gridPos": { "h": 10, "w": 12, "x": 12, "y": 46 },
      "id": 51,
      "options": { "legend": { "calcs": ["mean", "max"], "displayMode": "table", "placement": "bottom", "showLegend": true }, "tooltip": { "mode": "multi", "sort": "desc" } },
      "title": "Memory by Container",
      "type": "timeseries",
      "targets": [{ "expr": "sum by (pod, container) (container_memory_working_set_bytes{namespace=\"$namespace\", container!=\"\", container!=\"POD\"})", "legendFormat": "{{pod}}/{{container}}", "refId": "A" }]
    },
    {
      "collapsed": false,
      "gridPos": { "h": 1, "w": 24, "x": 0, "y": 56 },
      "id": 106,
      "panels": [],
      "title": "⚠️ Alerts & Issues",
      "type": "row"
    },
    {
      "datasource": { "type": "prometheus", "uid": "prometheus" },
      "fieldConfig": {
        "defaults": {
          "color": { "mode": "thresholds" },
          "mappings": [],
          "thresholds": { "mode": "absolute", "steps": [{ "color": "green", "value": null }, { "color": "red", "value": 1 }] },
          "unit": "short"
        },
        "overrides": []
      },
      "gridPos": { "h": 4, "w": 6, "x": 0, "y": 57 },
      "id": 60,
      "options": { "colorMode": "background", "graphMode": "none", "justifyMode": "center", "orientation": "auto", "reduceOptions": { "calcs": ["lastNotNull"], "fields": "", "values": false }, "textMode": "auto" },
      "title": "OOMKilled",
      "type": "stat",
      "targets": [{ "expr": "count(kube_pod_container_status_last_terminated_reason{namespace=\"$namespace\", reason=\"OOMKilled\"}) or vector(0)", "refId": "A" }]
    },
    {
      "datasource": { "type": "prometheus", "uid": "prometheus" },
      "fieldConfig": {
        "defaults": {
          "color": { "mode": "thresholds" },
          "mappings": [],
          "thresholds": { "mode": "absolute", "steps": [{ "color": "green", "value": null }, { "color": "red", "value": 1 }] },
          "unit": "short"
        },
        "overrides": []
      },
      "gridPos": { "h": 4, "w": 6, "x": 6, "y": 57 },
      "id": 61,
      "options": { "colorMode": "background", "graphMode": "none", "justifyMode": "center", "orientation": "auto", "reduceOptions": { "calcs": ["lastNotNull"], "fields": "", "values": false }, "textMode": "auto" },
      "title": "CrashLoopBackOff",
      "type": "stat",
      "targets": [{ "expr": "count(kube_pod_container_status_waiting_reason{namespace=\"$namespace\", reason=\"CrashLoopBackOff\"}) or vector(0)", "refId": "A" }]
    },
    {
      "datasource": { "type": "prometheus", "uid": "prometheus" },
      "fieldConfig": {
        "defaults": {
          "color": { "mode": "thresholds" },
          "mappings": [],
          "thresholds": { "mode": "absolute", "steps": [{ "color": "green", "value": null }, { "color": "red", "value": 1 }] },
          "unit": "short"
        },
        "overrides": []
      },
      "gridPos": { "h": 4, "w": 6, "x": 12, "y": 57 },
      "id": 62,
      "options": { "colorMode": "background", "graphMode": "none", "justifyMode": "center", "orientation": "auto", "reduceOptions": { "calcs": ["lastNotNull"], "fields": "", "values": false }, "textMode": "auto" },
      "title": "Containers Not Ready",
      "type": "stat",
      "targets": [{ "expr": "count(kube_pod_container_status_ready{namespace=\"$namespace\", ready=\"false\"}) or vector(0)", "refId": "A" }]
    },
    {
      "datasource": { "type": "prometheus", "uid": "prometheus" },
      "fieldConfig": {
        "defaults": {
          "color": { "mode": "thresholds" },
          "mappings": [],
          "thresholds": { "mode": "absolute", "steps": [{ "color": "green", "value": null }, { "color": "orange", "value": 0.01 }, { "color": "red", "value": 0.1 }] },
          "unit": "percentunit"
        },
        "overrides": []
      },
      "gridPos": { "h": 4, "w": 6, "x": 18, "y": 57 },
      "id": 63,
      "options": { "colorMode": "background", "graphMode": "area", "justifyMode": "center", "orientation": "auto", "reduceOptions": { "calcs": ["mean"], "fields": "", "values": false }, "textMode": "auto" },
      "title": "CPU Throttling",
      "type": "stat",
      "targets": [{ "expr": "sum(rate(container_cpu_cfs_throttled_periods_total{namespace=\"$namespace\"}[5m])) / sum(rate(container_cpu_cfs_periods_total{namespace=\"$namespace\"}[5m])) or vector(0)", "refId": "A" }]
    }
  ],
  "refresh": "30s",
  "schemaVersion": 38,
  "style": "dark",
  "tags": ["kubernetes", "namespace", "overview"],
  "templating": {
    "list": [
      {
        "current": {},
        "datasource": { "type": "prometheus", "uid": "prometheus" },
        "definition": "label_values(kube_pod_info, namespace)",
        "hide": 0,
        "includeAll": false,
        "label": "Namespace",
        "multi": false,
        "name": "namespace",
        "options": [],
        "query": { "query": "label_values(kube_pod_info, namespace)", "refId": "StandardVariableQuery" },
        "refresh": 2,
        "regex": "",
        "skipUrlSync": false,
        "sort": 1,
        "type": "query"
      }
    ]
  },
  "time": { "from": "now-1h", "to": "now" },
  "timepicker": {},
  "timezone": "",
  "title": "Namespace Overview",
  "uid": "namespace-overview",
  "version": 1,
  "weekStart": ""
}
